functime-0.9.5.dist-info/METADATA
functime-0.9.5.dist-info/WHEEL
functime-0.9.5.dist-info/license_files/LICENSE
functime/feature_extractors.py
functime/type_alias.py
functime/base/forecaster.py
functime/base/transformer.py
functime/base/metric.py
functime/base/model.py
functime/base/__init__.py
functime/cross_validation.py
functime/metrics/point.py
functime/metrics/probabilistic.py
functime/metrics/__init__.py
functime/metrics/multi_objective.py
functime/conformal.py
functime/plotting.py
functime/evaluation.py
functime/conversion.py
functime/llm/api.py
functime/llm/common.py
functime/llm/__init__.py
functime/llm/formatting.py
functime/forecasting/automl.py
functime/forecasting/_reduction.py
functime/forecasting/_ar.py
functime/forecasting/_regressors.py
functime/forecasting/snaive.py
functime/forecasting/censored.py
functime/forecasting/lightgbm.py
functime/forecasting/knn.py
functime/forecasting/catboost.py
functime/forecasting/linear.py
functime/forecasting/xgboost.py
functime/forecasting/_evaluate.py
functime/forecasting/naive.py
functime/forecasting/lance.py
functime/forecasting/__init__.py
functime/forecasting/elite.py
functime/_utils.py
functime/ranges.py
functime/backtesting.py
functime/__init__.py
functime/offsets.py
functime/preprocessing.py
functime/seasonality/calendar.py
functime/seasonality/fourier.py
functime/seasonality/__init__.py
functime/_functime_rust.pypy310-pp73-x86_64-linux-gnu.so
functime-0.9.5.dist-info/RECORD
