Metadata-Version: 2.1
Name: functime
Version: 0.9.5
Classifier: Development Status :: 4 - Beta
Classifier: Intended Audience :: Developers
Classifier: Intended Audience :: Science/Research
Classifier: Programming Language :: Python :: 3 :: Only
Classifier: Programming Language :: Python :: 3.8
Classifier: Programming Language :: Python :: 3.9
Classifier: Programming Language :: Python :: 3.10
Classifier: Programming Language :: Python :: 3.11
Classifier: Programming Language :: Python :: 3.12
Classifier: Topic :: Scientific/Engineering
Classifier: Topic :: Software Development :: Libraries :: Python Modules
Requires-Dist: cloudpickle
Requires-Dist: flaml <3, >=2.0.2
Requires-Dist: holidays
Requires-Dist: numpy
Requires-Dist: polars >=0.20.7
Requires-Dist: scikit-learn <2, >=1.2.2
Requires-Dist: scipy
Requires-Dist: tqdm
Requires-Dist: typing-extensions ; python_version < '3.10'
Requires-Dist: pyarrow ; extra == 'ann'
Requires-Dist: pylance ; extra == 'ann'
Requires-Dist: catboost ; extra == 'cat'
Requires-Dist: pre-commit ; extra == 'dev'
Requires-Dist: functime[doc,plot,test] ; extra == 'dev'
Requires-Dist: jupyterlab ; extra == 'doc'
Requires-Dist: mkdocs ; extra == 'doc'
Requires-Dist: mkdocs-jupyter ; extra == 'doc'
Requires-Dist: mkdocs-material ; extra == 'doc'
Requires-Dist: mkdocstrings-python ; extra == 'doc'
Requires-Dist: lightgbm ; extra == 'lgb'
Requires-Dist: openai ; extra == 'llm'
Requires-Dist: tabulate ; extra == 'llm'
Requires-Dist: tenacity ; extra == 'llm'
Requires-Dist: tiktoken ; extra == 'llm'
Requires-Dist: kaleido ==0.2.1 ; extra == 'plot'
Requires-Dist: pandas ; extra == 'plot'
Requires-Dist: plotly ; extra == 'plot'
Requires-Dist: aeon <0.5.0 ; extra == 'test'
Requires-Dist: coverage[toml] ; extra == 'test'
Requires-Dist: fastapi ; extra == 'test'
Requires-Dist: joblib ; extra == 'test'
Requires-Dist: mlforecast ==0.8.1 ; extra == 'test'
Requires-Dist: pandas ; extra == 'test'
Requires-Dist: pytest ; extra == 'test'
Requires-Dist: pytest-benchmark ; extra == 'test'
Requires-Dist: pytest-memray ; extra == 'test'
Requires-Dist: pytest-timeout ; extra == 'test'
Requires-Dist: statsmodels ; extra == 'test'
Requires-Dist: tsfresh ; extra == 'test'
Requires-Dist: pyarrow ; extra == 'xgb'
Requires-Dist: xgboost ; extra == 'xgb'
Provides-Extra: ann
Provides-Extra: cat
Provides-Extra: dev
Provides-Extra: doc
Provides-Extra: lgb
Provides-Extra: llm
Provides-Extra: plot
Provides-Extra: test
Provides-Extra: xgb
License-File: LICENSE
Summary: Time-series machine learning at scale.
Author-email: functime Team <team@functime.ai>, Chris Lo <chris@functime.ai>, Daryl Lim <daryl@functime.ai>
Requires-Python: >=3.8
